cook_containers/__init__.py
cook_containers/main.py
cook_containers/src/__init__.py
cook_containers/src/create_container_template.py
cook_containers/src/manage_containers.py
cook_containers/src/read_configurations.py
cook_containers-0.1.dist-info/METADATA
cook_containers-0.1.dist-info/WHEEL
cook_containers-0.1.dist-info/entry_points.txt
cook_containers-0.1.dist-info/top_level.txt
cook_containers-0.1.dist-info/RECORD
